paper_trading/__init__.py
paper_trading/api/__init__.py
paper_trading/api/db.py
paper_trading/api/pytdx_api.py
paper_trading/api/tushare_api.py
paper_trading/app/__init__.py
paper_trading/app/errors.py
paper_trading/app/ext.py
paper_trading/app/static/css/bootstrap.css
paper_trading/app/static/css/datatables.min.css
paper_trading/app/static/css/font-awesome.min.css
paper_trading/app/static/css/landing.css
paper_trading/app/static/css/plugin.css
paper_trading/app/static/css/style.css
paper_trading/app/static/font/fontawesome-webfont.eot
paper_trading/app/static/font/fontawesome-webfont.svg
paper_trading/app/static/font/fontawesome-webfont.ttf
paper_trading/app/static/font/fontawesome-webfont.woff
paper_trading/app/static/font/FontAwesome.otf
paper_trading/app/static/highcharts/drag-panes.js
paper_trading/app/static/highcharts/exporting.js
paper_trading/app/static/highcharts/highcharts-more.js
paper_trading/app/static/highcharts/highcharts-zh_CN.js
paper_trading/app/static/highcharts/highcharts.js
paper_trading/app/static/highcharts/highstock.js
paper_trading/app/static/images/avatar.jpg
paper_trading/app/static/images/first_icon.png
paper_trading/app/static/images/render-1-thumb.jpg
paper_trading/app/static/images/render-1.jpg
paper_trading/app/static/images/render-2-thumb.jpg
paper_trading/app/static/images/render-2.jpg
paper_trading/app/static/images/render-3-thumb.jpg
paper_trading/app/static/images/render-3.jpg
paper_trading/app/static/images/render-4-thumb.jpg
paper_trading/app/static/images/render-4.jpg
paper_trading/app/static/images/responsive.png
paper_trading/app/static/js/app.data.js
paper_trading/app/static/js/app.js
paper_trading/app/static/js/app.plugin.js
paper_trading/app/static/js/bootstrap.js
paper_trading/app/static/js/charts/easypiechart/jquery.easy-pie-chart.js
paper_trading/app/static/js/charts/sparkline/jquery.sparkline.min.js
paper_trading/app/static/js/combodate/combodate.js
paper_trading/app/static/js/combodate/moment.min.js
paper_trading-1.2.2.dist-info/entry_points.txt
paper_trading-1.2.2.dist-info/LICENSE
paper_trading-1.2.2.dist-info/WHEEL
paper_trading-1.2.2.dist-info/METADATA
paper_trading-1.2.2.dist-info/RECORD
